{
  "routes": [
    {
      "method": "GET",
      "path": "/legends",
      "handler": "legends.find",
      "config": {
        "policies": []
      }
    },
    {
      "method": "GET",
      "path": "/legends/count",
      "handler": "legends.count",
      "config": {
        "policies": []
      }
    },
    {
      "method": "GET",
      "path": "/legends/:id",
      "handler": "legends.findOne",
      "config": {
        "policies": []
      }
    },
    {
      "method": "POST",
      "path": "/legends",
      "handler": "legends.create",
      "config": {
        "policies": []
      }
    },
    {
      "method": "PUT",
      "path": "/legends/:id",
      "handler": "legends.update",
      "config": {
        "policies": []
      }
    },
    {
      "method": "DELETE",
      "path": "/legends/:id",
      "handler": "legends.delete",
      "config": {
        "policies": []
      }
    }
  ]
}
